{
  "root_group": {
    "name": "",
    "path": "",
    "id": "d41d8cd98f00b204e9800998ecf8427e",
    "groups": [],
    "checks": [
        {
          "passes": 10000,
          "fails": 0,
          "name": "is status 200",
          "path": "::is status 200",
          "id": "548d37ca5f33793206f7832e7cea54fb"
        }
      ]
  },
  "options": {
    "summaryTimeUnit": "ms",
    "noColor": false,
    "summaryTrendStats": [
      "avg",
      "min",
      "med",
      "max",
      "p(50)",
      "p(90)",
      "p(95)",
      "p(99)",
      "p(99.99)",
      "count"
    ]
  },
  "state": {
    "isStdErrTTY": false,
    "testRunDurationMs": 18068.48127,
    "isStdOutTTY": false
  },
  "metrics": {
    "http_req_waiting": {
      "type": "trend",
      "contains": "time",
      "values": {
        "p(90)": 1.868804,
        "count": 10000,
        "p(50)": 1.3259005,
        "min": 0.662148,
        "med": 1.3259005,
        "max": 31.988833,
        "p(95)": 2.3627107499999997,
        "p(99)": 6.4860004900000305,
        "p(99.99)": 28.114858436197263,
        "avg": 1.4945064851000092
      }
    },
    "iterations": {
      "type": "counter",
      "contains": "default",
      "values": {
        "count": 10000,
        "rate": 553.4499469307085
      }
    },
    "response_time": {
      "type": "trend",
      "contains": "default",
      "values": {
        "p(90)": 1.9968698,
        "count": 10000,
        "avg": 1.5912492811000027,
        "min": 0.694924,
        "p(50)": 1.409492,
        "p(95)": 2.5150409999999974,
        "p(99)": 6.798961630000015,
        "p(99.99)": 31.45707803989955,
        "med": 1.409492,
        "max": 32.097413
      }
    },
    "data_sent": {
      "type": "counter",
      "contains": "data",
      "values": {
        "count": 3720000,
        "rate": 205883.38025822357
      }
    },
    "http_req_connecting": {
      "type": "trend",
      "contains": "time",
      "values": {
        "avg": 0.0016309542,
        "max": 0.330716,
        "p(50)": 0,
        "p(90)": 0,
        "count": 10000,
        "min": 0,
        "med": 0,
        "p(95)": 0,
        "p(99)": 0.0010388800000226766,
        "p(99.99)": 0.24987008539994282
      }
    },
    "vus": {
      "type": "gauge",
      "contains": "default",
      "values": {
        "value": 1,
        "min": 1,
        "max": 1
      }
    },
    "http_req_duration": {
      "values": {
        "med": 1.409492,
        "p(95)": 2.5150409999999974,
        "count": 10000,
        "avg": 1.5912492811000027,
        "min": 0.694924,
        "max": 32.097413,
        "p(50)": 1.409492,
        "p(90)": 1.9968698,
        "p(99)": 6.798961630000015,
        "p(99.99)": 31.45707803989955
      },
      "type": "trend",
      "contains": "time"
    },
    "http_req_blocked": {
      "contains": "time",
      "values": {
        "p(50)": 0.004521,
        "p(99)": 0.17232174000000125,
        "med": 0.004521,
        "max": 0.429561,
        "p(90)": 0.0061922,
        "p(95)": 0.007714099999999999,
        "p(99.99)": 0.3485321036999427,
        "count": 10000,
        "avg": 0.007363603899999988,
        "min": 0.001258
      },
      "type": "trend"
    },
    "http_req_tls_handshaking": {
      "values": {
        "min": 0,
        "max": 0,
        "p(50)": 0,
        "p(90)": 0,
        "p(99)": 0,
        "count": 10000,
        "avg": 0,
        "med": 0,
        "p(95)": 0,
        "p(99.99)": 0
      },
      "type": "trend",
      "contains": "time"
    },
    "http_req_receiving": {
      "type": "trend",
      "contains": "time",
      "values": {
        "med": 0.061425,
        "p(50)": 0.061425,
        "p(90)": 0.10047360000000002,
        "p(95)": 0.13175419999999993,
        "p(99.99)": 8.812174443385627,
        "count": 10000,
        "avg": 0.07781744540000039,
        "min": 0.022851,
        "max": 29.134576,
        "p(99)": 0.2645654800000002
      }
    },
    "response_size": {
      "type": "trend",
      "contains": "default",
      "values": {
        "avg": 511.48,
        "min": 460,
        "p(50)": 512,
        "p(99)": 512,
        "p(99.99)": 512,
        "count": 10000,
        "med": 512,
        "max": 512,
        "p(90)": 512,
        "p(95)": 512
      }
    },
    "vus_max": {
      "type": "gauge",
      "contains": "default",
      "values": {
        "value": 1,
        "min": 1,
        "max": 1
      }
    },
    "http_req_duration{expected_response:true}": {
      "type": "trend",
      "contains": "time",
      "values": {
        "avg": 1.5912492811000027,
        "med": 1.409492,
        "p(50)": 1.409492,
        "p(95)": 2.5150409999999974,
        "p(99)": 6.798961630000015,
        "min": 0.694924,
        "max": 32.097413,
        "p(90)": 1.9968698,
        "p(99.99)": 31.45707803989955,
        "count": 10000
      }
    },
    "http_req_sending": {
      "type": "trend",
      "contains": "time",
      "values": {
        "p(50)": 0.0174785,
        "avg": 0.0189253506,
        "min": 0.005027,
        "med": 0.0174785,
        "p(99)": 0.06018525000000001,
        "p(99.99)": 0.3244108028999519,
        "count": 10000,
        "max": 0.392433,
        "p(90)": 0.0238691,
        "p(95)": 0.029526599999999948
      }
    },
    "checks": {
      "contains": "default",
      "values": {
        "rate": 1,
        "passes": 10000,
        "fails": 0
      },
      "type": "rate"
    },
    "http_reqs": {
      "type": "counter",
      "contains": "default",
      "values": {
        "rate": 553.4499469307085,
        "count": 10000
      }
    },
    "reponse_size_body": {
      "type": "trend",
      "contains": "default",
      "values": {
        "p(50)": 150,
        "p(95)": 150,
        "p(99.99)": 150,
        "count": 10000,
        "min": 150,
        "med": 150,
        "p(90)": 150,
        "p(99)": 150,
        "avg": 150,
        "max": 150
      }
    },
    "data_received": {
      "type": "counter",
      "contains": "data",
      "values": {
        "count": 5587100,
        "rate": 309218.01984965615
      }
    },
    "iteration_duration": {
      "type": "trend",
      "contains": "time",
      "values": {
        "p(99.99)": 31.72177655939958,
        "count": 10000,
        "avg": 1.789893821700002,
        "max": 32.317311,
        "p(90)": 2.2332618,
        "p(99)": 7.188862410000029,
        "min": 0.77468,
        "med": 1.598403,
        "p(50)": 1.598403,
        "p(95)": 2.814834899999999
      }
    },
    "http_req_failed": {
      "contains": "default",
      "values": {
        "rate": 0,
        "passes": 0,
        "fails": 10000
      },
      "type": "rate"
    }
  }
}