{
  "state": {
    "isStdOutTTY": false,
    "isStdErrTTY": false,
    "testRunDurationMs": 7597.852541
  },
  "metrics": {
    "http_req_connecting": {
      "type": "trend",
      "contains": "time",
      "values": {
        "p(50)": 0,
        "p(99.99)": 0.2482835839999868,
        "min": 0,
        "med": 0,
        "p(90)": 0,
        "p(95)": 0,
        "p(99)": 0,
        "count": 1000,
        "avg": 0.00027583999999999996,
        "max": 0.27584
      }
    },
    "http_req_tls_handshaking": {
      "type": "trend",
      "contains": "time",
      "values": {
        "max": 0,
        "p(50)": 0,
        "p(90)": 0,
        "p(95)": 0,
        "min": 0,
        "med": 0,
        "p(99.99)": 0,
        "count": 1000,
        "avg": 0,
        "p(99)": 0
      }
    },
    "http_req_receiving": {
      "type": "trend",
      "contains": "time",
      "values": {
        "avg": 0.267920223,
        "min": 0.055603,
        "max": 47.768889,
        "p(99.99)": 46.32041502389931,
        "count": 1000,
        "med": 0.09212000000000001,
        "p(50)": 0.09212000000000001,
        "p(90)": 0.1643237,
        "p(95)": 0.24946199999999988,
        "p(99)": 0.5312003299999878
      }
    },
    "checks": {
      "type": "rate",
      "contains": "default",
      "values": {
        "rate": 1,
        "passes": 1000,
        "fails": 0
      }
    },
    "http_req_duration": {
      "type": "trend",
      "contains": "time",
      "values": {
        "max": 72.713409,
        "p(95)": 23.782920549999957,
        "p(99.99)": 71.96612712989965,
        "avg": 7.322991719000007,
        "min": 2.931209,
        "med": 4.5480025,
        "count": 1000,
        "p(50)": 4.5480025,
        "p(90)": 10.3205174,
        "p(99)": 52.26319784
      }
    },
    "http_req_failed": {
      "type": "rate",
      "contains": "default",
      "values": {
        "rate": 0,
        "passes": 0,
        "fails": 1000
      }
    },
    "vus": {
      "type": "gauge",
      "contains": "default",
      "values": {
        "value": 1,
        "min": 1,
        "max": 1
      }
    },
    "vus_max": {
      "type": "gauge",
      "contains": "default",
      "values": {
        "value": 1,
        "min": 1,
        "max": 1
      }
    },
    "data_received": {
      "type": "counter",
      "contains": "data",
      "values": {
        "count": 1110152,
        "rate": 146113.9175851768
      }
    },
    "reponse_size_body": {
      "type": "trend",
      "contains": "default",
      "values": {
        "p(90)": 609,
        "min": 609,
        "med": 609,
        "p(50)": 609,
        "p(95)": 609,
        "p(99)": 609,
        "p(99.99)": 609,
        "count": 1000,
        "avg": 609,
        "max": 609
      }
    },
    "http_req_duration{expected_response:true}": {
      "type": "trend",
      "contains": "time",
      "values": {
        "p(90)": 10.3205174,
        "p(99)": 52.26319784,
        "avg": 7.322991719000007,
        "min": 2.931209,
        "med": 4.5480025,
        "p(50)": 4.5480025,
        "max": 72.713409,
        "p(95)": 23.782920549999957,
        "p(99.99)": 71.96612712989965,
        "count": 1000
      }
    },
    "http_req_blocked": {
      "values": {
        "avg": 0.006283358999999993,
        "min": 0.002513,
        "max": 0.361454,
        "p(50)": 0.005232499999999999,
        "p(90)": 0.0076654,
        "p(95)": 0.0092354,
        "count": 1000,
        "med": 0.005232499999999999,
        "p(99)": 0.01753883999999999,
        "p(99.99)": 0.3345568240999871
      },
      "type": "trend",
      "contains": "time"
    },
    "response_time": {
      "type": "trend",
      "contains": "default",
      "values": {
        "avg": 7.322991719000007,
        "min": 2.931209,
        "p(90)": 10.3205174,
        "p(95)": 23.782920549999957,
        "p(99.99)": 71.96612712989965,
        "med": 4.5480025,
        "max": 72.713409,
        "p(50)": 4.5480025,
        "p(99)": 52.26319784,
        "count": 1000
      }
    },
    "http_reqs": {
      "type": "counter",
      "contains": "default",
      "values": {
        "count": 1000,
        "rate": 131.61613687601047
      }
    },
    "iteration_duration": {
      "values": {
        "p(99)": 52.64561034,
        "count": 1000,
        "p(50)": 4.7958805,
        "p(90)": 10.5481861,
        "p(95)": 24.121457399999958,
        "max": 72.99177,
        "p(99.99)": 72.25056404789964,
        "avg": 7.576222407999995,
        "min": 3.127596,
        "med": 4.7958805
      },
      "type": "trend",
      "contains": "time"
    },
    "http_req_waiting": {
      "values": {
        "p(99)": 52.10679581,
        "p(99.99)": 71.83512166699964,
        "avg": 7.031853464,
        "min": 2.84463,
        "med": 4.398531999999999,
        "p(90)": 8.908056400000001,
        "max": 72.598025,
        "p(50)": 4.398531999999999,
        "p(95)": 22.72316169999999,
        "count": 1000
      },
      "type": "trend",
      "contains": "time"
    },
    "iterations": {
      "type": "counter",
      "contains": "default",
      "values": {
        "count": 1000,
        "rate": 131.61613687601047
      }
    },
    "response_size": {
      "type": "trend",
      "contains": "default",
      "values": {
        "p(50)": 1059,
        "p(90)": 1059,
        "p(95)": 1059,
        "p(99)": 1059,
        "p(99.99)": 1059,
        "count": 1000,
        "avg": 1059,
        "med": 1059,
        "max": 1059,
        "min": 1059
      }
    },
    "data_sent": {
      "type": "counter",
      "contains": "data",
      "values": {
        "rate": 53830.99998228828,
        "count": 409000
      }
    },
    "http_req_sending": {
      "type": "trend",
      "contains": "time",
      "values": {
        "avg": 0.02321803199999996,
        "min": 0.012082,
        "max": 0.162363,
        "p(50)": 0.021463999999999997,
        "p(95)": 0.034763999999999996,
        "count": 1000,
        "med": 0.021463999999999997,
        "p(90)": 0.030650500000000004,
        "p(99)": 0.05088933999999999,
        "p(99.99)": 0.16180445909999974
      }
    }
  },
  "root_group": {
    "name": "",
    "path": "",
    "id": "d41d8cd98f00b204e9800998ecf8427e",
    "groups": [],
    "checks": [
        {
          "name": "is status 200",
          "path": "::is status 200",
          "id": "548d37ca5f33793206f7832e7cea54fb",
          "passes": 1000,
          "fails": 0
        }
      ]
  },
  "options": {
    "summaryTimeUnit": "ms",
    "noColor": false,
    "summaryTrendStats": [
      "avg",
      "min",
      "med",
      "max",
      "p(50)",
      "p(90)",
      "p(95)",
      "p(99)",
      "p(99.99)",
      "count"
    ]
  }
}