{
  "root_group": {
    "name": "",
    "path": "",
    "id": "d41d8cd98f00b204e9800998ecf8427e",
    "groups": [],
    "checks": [
        {
          "passes": 10000,
          "fails": 0,
          "name": "is status 200",
          "path": "::is status 200",
          "id": "548d37ca5f33793206f7832e7cea54fb"
        }
      ]
  },
  "options": {
    "summaryTrendStats": [
      "avg",
      "min",
      "med",
      "max",
      "p(50)",
      "p(90)",
      "p(95)",
      "p(99)",
      "p(99.99)",
      "count"
    ],
    "summaryTimeUnit": "ms",
    "noColor": false
  },
  "state": {
    "isStdOutTTY": false,
    "isStdErrTTY": false,
    "testRunDurationMs": 29874.23246
  },
  "metrics": {
    "response_time": {
      "type": "trend",
      "contains": "default",
      "values": {
        "p(99)": 4.446055980000001,
        "p(99.99)": 9.178864840797647,
        "min": 1.587476,
        "max": 12.50694,
        "p(50)": 2.7221985,
        "p(90)": 3.1769526,
        "p(95)": 3.383129299999999,
        "avg": 2.7371119701000084,
        "med": 2.7221985,
        "count": 10000
      }
    },
    "reponse_size_body": {
      "type": "trend",
      "contains": "default",
      "values": {
        "avg": 150,
        "min": 150,
        "max": 150,
        "p(99)": 150,
        "count": 10000,
        "med": 150,
        "p(50)": 150,
        "p(90)": 150,
        "p(95)": 150,
        "p(99.99)": 150
      }
    },
    "vus": {
      "values": {
        "min": 1,
        "max": 1,
        "value": 1
      },
      "type": "gauge",
      "contains": "default"
    },
    "http_req_blocked": {
      "type": "trend",
      "contains": "time",
      "values": {
        "med": 0.005539,
        "max": 0.302091,
        "count": 10000,
        "p(90)": 0.006843,
        "p(95)": 0.008070299999999996,
        "p(99)": 0.015340290000000029,
        "p(99.99)": 0.08318989229984518,
        "avg": 0.005783262799999983,
        "min": 0.002004,
        "p(50)": 0.005539
      }
    },
    "http_req_waiting": {
      "type": "trend",
      "contains": "time",
      "values": {
        "count": 10000,
        "avg": 2.591080371899989,
        "min": 1.361621,
        "p(90)": 3.0086224,
        "p(99.99)": 9.062237695597704,
        "p(99)": 4.264392160000002,
        "med": 2.5717885000000003,
        "max": 12.308869,
        "p(50)": 2.5717885000000003,
        "p(95)": 3.19223805
      }
    },
    "http_req_duration": {
      "type": "trend",
      "contains": "time",
      "values": {
        "p(95)": 3.383129299999999,
        "p(99.99)": 9.178864840797647,
        "count": 10000,
        "avg": 2.7371119701000084,
        "max": 12.50694,
        "p(90)": 3.1769526,
        "p(99)": 4.446055980000001,
        "min": 1.587476,
        "med": 2.7221985,
        "p(50)": 2.7221985
      }
    },
    "data_received": {
      "type": "counter",
      "contains": "data",
      "values": {
        "count": 6029444,
        "rate": 201827.578602165
      }
    },
    "iterations": {
      "type": "counter",
      "contains": "default",
      "values": {
        "rate": 334.73663343115055,
        "count": 10000
      }
    },
    "vus_max": {
      "type": "gauge",
      "contains": "default",
      "values": {
        "value": 1,
        "min": 1,
        "max": 1
      }
    },
    "http_req_receiving": {
      "type": "trend",
      "contains": "time",
      "values": {
        "p(99.99)": 3.517796552599798,
        "med": 0.09437100000000001,
        "max": 3.803294,
        "p(90)": 0.20996720000000005,
        "p(95)": 0.2432836499999998,
        "p(99)": 0.31525564000000006,
        "count": 10000,
        "avg": 0.12338792469999987,
        "min": 0.040303,
        "p(50)": 0.09437100000000001
      }
    },
    "checks": {
      "type": "rate",
      "contains": "default",
      "values": {
        "rate": 1,
        "passes": 10000,
        "fails": 0
      }
    },
    "http_req_connecting": {
      "contains": "time",
      "values": {
        "min": 0,
        "med": 0,
        "p(99)": 0,
        "p(99.99)": 0.000020881599852320507,
        "count": 10000,
        "avg": 0.0000208816,
        "max": 0.208816,
        "p(50)": 0,
        "p(90)": 0,
        "p(95)": 0
      },
      "type": "trend"
    },
    "data_sent": {
      "type": "counter",
      "contains": "data",
      "values": {
        "count": 3720000,
        "rate": 124522.02763638801
      }
    },
    "http_reqs": {
      "contains": "default",
      "values": {
        "count": 10000,
        "rate": 334.73663343115055
      },
      "type": "counter"
    },
    "http_req_tls_handshaking": {
      "type": "trend",
      "contains": "time",
      "values": {
        "min": 0,
        "p(50)": 0,
        "p(90)": 0,
        "avg": 0,
        "max": 0,
        "p(95)": 0,
        "p(99)": 0,
        "p(99.99)": 0,
        "count": 10000,
        "med": 0
      }
    },
    "http_req_sending": {
      "contains": "time",
      "values": {
        "p(50)": 0.022348,
        "p(99.99)": 0.3538664792999117,
        "avg": 0.022643673500000037,
        "min": 0.007833,
        "med": 0.022348,
        "max": 0.478647,
        "p(90)": 0.026548099999999998,
        "p(95)": 0.028739449999999993,
        "p(99)": 0.04864858000000006,
        "count": 10000
      },
      "type": "trend"
    },
    "http_req_duration{expected_response:true}": {
      "type": "trend",
      "contains": "time",
      "values": {
        "min": 1.587476,
        "max": 12.50694,
        "p(90)": 3.1769526,
        "p(95)": 3.383129299999999,
        "p(99)": 4.446055980000001,
        "p(99.99)": 9.178864840797647,
        "avg": 2.7371119701000084,
        "p(50)": 2.7221985,
        "count": 10000,
        "med": 2.7221985
      }
    },
    "response_size": {
      "contains": "default",
      "values": {
        "p(90)": 531,
        "avg": 531,
        "min": 531,
        "med": 531,
        "max": 531,
        "count": 10000,
        "p(50)": 531,
        "p(95)": 531,
        "p(99)": 531,
        "p(99.99)": 531
      },
      "type": "trend"
    },
    "iteration_duration": {
      "contains": "time",
      "values": {
        "min": 1.727809,
        "max": 13.287916,
        "p(90)": 3.4318094000000006,
        "p(95)": 3.6438700500000003,
        "p(99)": 4.70555267,
        "p(99.99)": 9.443494480597282,
        "count": 10000,
        "avg": 2.967134843200009,
        "med": 2.9547985,
        "p(50)": 2.9547985
      },
      "type": "trend"
    },
    "http_req_failed": {
      "contains": "default",
      "values": {
        "rate": 0,
        "passes": 0,
        "fails": 10000
      },
      "type": "rate"
    }
  }
}